clips2share/__init__.py
clips2share/clips2share.py
clips2share/qbittorrent_client.py
clips2share/fonts/DejaVuSans-Bold.ttf
clips2share/fonts/DejaVuSans.ttf
clips2share/templates/default_bbcode.jinja
clips2share-0.0.11.dist-info/licenses/LICENSE
clips2share-0.0.11.dist-info/METADATA
clips2share-0.0.11.dist-info/WHEEL
clips2share-0.0.11.dist-info/entry_points.txt
clips2share-0.0.11.dist-info/top_level.txt
clips2share-0.0.11.dist-info/RECORD
