Metadata-Version: 2.4
Name: clips2share
Version: 0.0.11
Summary: Helper for creating adult torrents
Author: c2s
Project-URL: Homepage, https://codeberg.org/c2s/clips2share
Project-URL: Repository, https://codeberg.org/c2s/clips2share.git
Project-URL: Bug Tracker, https://codeberg.org/c2s/clips2share/issues
Project-URL: Changelog, https://codeberg.org/c2s/clips2share/releases
Keywords: torrent,clips4sale,thumbnail
Classifier: Development Status :: 4 - Beta
Classifier: Programming Language :: Python
Classifier: Environment :: Console
Requires-Python: >=3.11
License-File: LICENSE
Requires-Dist: Jinja2
Requires-Dist: platformdirs
Requires-Dist: requests
Requires-Dist: torf
Requires-Dist: vcsi
Dynamic: license-file
